mtdl/__init__.py
mtdl/cli.py
mtdl/downloader.py
mtdl/metadata.py
mtdl/utils.py
mtdl-5.6.dist-info/LICENSE-en
mtdl-5.6.dist-info/METADATA
mtdl-5.6.dist-info/WHEEL
mtdl-5.6.dist-info/entry_points.txt
mtdl-5.6.dist-info/top_level.txt
mtdl-5.6.dist-info/RECORD
