Metadata-Version: 2.1
Name: mtdl
Version: 5.6
Summary: Python multi-thread file downloader.
Author: Bill Loic
Author-email: billloic6@gmail.com
License: Copyright (C) 2024 BillLoic
Classifier: Programming Language :: Python
Classifier: Programming Language :: Python :: 3 :: Only
Classifier: Topic :: Internet
Classifier: Topic :: Internet :: WWW/HTTP
License-File: LICENSE-en
Requires-Dist: colorama
Requires-Dist: tqdm
Requires-Dist: requests
